docuvert/__init__.py
docuvert/__main__.py
docuvert/cli.py
docuvert/converters/__init__.py
docuvert/converters/csv2docx.py
docuvert/converters/csv2md.py
docuvert/converters/csv2pdf.py
docuvert/converters/csv2tex.py
docuvert/converters/csv2txt.py
docuvert/converters/csv2xlsx.py
docuvert/converters/docx2csv.py
docuvert/converters/docx2md.py
docuvert/converters/docx2pdf.py
docuvert/converters/docx2tex.py
docuvert/converters/docx2txt.py
docuvert/converters/docx2xlsx.py
docuvert/converters/heic2jpeg.py
docuvert/converters/heic2jpg.py
docuvert/converters/heic2pdf.py
docuvert/converters/heic2png.py
docuvert/converters/html2docx.py
docuvert/converters/html2jpg.py
docuvert/converters/html2md.py
docuvert/converters/html2pdf.py
docuvert/converters/html2png.py
docuvert/converters/html2png_new.py
docuvert/converters/html2pptx.py
docuvert/converters/html2pptx_enhanced.py
docuvert/converters/html2pptx_visual.py
docuvert/converters/jpeg2heic.py
docuvert/converters/jpeg2md.py
docuvert/converters/jpeg2pdf.py
docuvert/converters/jpeg2png.py
docuvert/converters/jpg2heic.py
docuvert/converters/jpg2md.py
docuvert/converters/jpg2pdf.py
docuvert/converters/jpg2png.py
docuvert/converters/md2csv.py
docuvert/converters/md2docx.py
docuvert/converters/md2html.py
docuvert/converters/md2pdf.py
docuvert/converters/md2tex.py
docuvert/converters/md2txt.py
docuvert/converters/md2xlsx.py
docuvert/converters/odt2md.py
docuvert/converters/pdf2csv.py
docuvert/converters/pdf2docx.py
docuvert/converters/pdf2heic.py
docuvert/converters/pdf2jpeg.py
docuvert/converters/pdf2jpg.py
docuvert/converters/pdf2md.py
docuvert/converters/pdf2png.py
docuvert/converters/pdf2tex.py
docuvert/converters/pdf2txt.py
docuvert/converters/pdf2xlsx.py
docuvert/converters/png2heic.py
docuvert/converters/png2jpeg.py
docuvert/converters/png2jpg.py
docuvert/converters/png2md.py
docuvert/converters/png2pdf.py
docuvert/converters/ppt2md.py
docuvert/converters/ppt2pdf.py
docuvert/converters/pptx2md.py
docuvert-1.3.5.dist-info/licenses/LICENSE
docuvert-1.3.5.dist-info/METADATA
docuvert-1.3.5.dist-info/WHEEL
docuvert-1.3.5.dist-info/entry_points.txt
docuvert-1.3.5.dist-info/top_level.txt
docuvert-1.3.5.dist-info/RECORD
