Metadata-Version: 2.4
Name: docuvert
Version: 1.3.5
Summary: Universal document converter with 250+ format combinations. Multi-page PDF to image conversion with page selection. OCR-powered image to Markdown for high-accuracy text extraction. Enhanced image support with PNG/JPEG/JPG/HEIC cross-conversions and PDF↔image conversions. Features PowerPoint to Obsidian Markdown with image extraction, format preservation, and navigation links. Supports PDF, DOCX, PPTX, MD, TEX, CSV, XLSX, TXT, HEIC, JPG, PNG, HTML, RTF, ODT.
Home-page: https://github.com/avanomme/docuvert
Author: Vanox Tech
Author-email: Vanox Tech <dev@vanoxtech.com>
License: MIT
Project-URL: Homepage, https://github.com/avanomme/docuvert
Project-URL: Repository, https://github.com/avanomme/docuvert
Keywords: document converter,pdf,docx,powerpoint,obsidian,markdown,latex,csv,xlsx,file conversion,pandoc,pptx,image extraction
Classifier: Development Status :: 4 - Beta
Classifier: Intended Audience :: Developers
Classifier: Intended Audience :: End Users/Desktop
Classifier: Topic :: Text Processing
Classifier: Topic :: Office/Business :: Office Suites
Classifier: Topic :: Utilities
Classifier: Programming Language :: Python :: 3
Classifier: Programming Language :: Python :: 3.8
Classifier: Programming Language :: Python :: 3.9
Classifier: Programming Language :: Python :: 3.10
Classifier: Programming Language :: Python :: 3.11
Classifier: Programming Language :: Python :: 3.12
Classifier: License :: OSI Approved :: MIT License
Classifier: Operating System :: OS Independent
Requires-Python: >=3.8
License-File: LICENSE
Requires-Dist: pypandoc
Requires-Dist: pandas
Requires-Dist: openpyxl
Requires-Dist: python-docx
Requires-Dist: python-pptx
Requires-Dist: PyMuPDF
Requires-Dist: pdfplumber
Requires-Dist: pdf2docx
Requires-Dist: reportlab
Requires-Dist: tabulate
Requires-Dist: Jinja2
Requires-Dist: xlrd
Requires-Dist: playwright
Requires-Dist: selenium
Requires-Dist: webdriver-manager
Requires-Dist: Pillow
Requires-Dist: pillow-heif; platform_system != "Windows"
Requires-Dist: pytesseract
Requires-Dist: build>=1.2.2.post1
Requires-Dist: twine>=6.1.0
Dynamic: author
Dynamic: home-page
Dynamic: license-file
Dynamic: requires-python
